client/__init__.py
client/client.py
client/app/__init__.py
client/app/context_manager.py
client/app/context_structure_manager.py
client/app/discovery.py
client/app/elicitation.py
client/app/llm_router.py
client/app/logging.py
client/app/notifications.py
client/app/prompts.py
client/app/resources.py
client/app/subscribe.py
client/app/tools.py
fastestmcp/__init__.py
fastestmcp/cli.py
fastestmcp/demo.py
fastestmcp/setup.py
fastestmcp/cli/__init__.py
fastestmcp/cli/__main__.py
fastestmcp/cli/client_generator.py
fastestmcp/cli/file_generators.py
fastestmcp/cli/generators.py
fastestmcp/cli/main_generator.py
fastestmcp/cli/mono_server_generator.py
fastestmcp/cli/notification_generators.py
fastestmcp/cli/server_generator.py
fastestmcp/cli/structured_server_generator.py
fastestmcp/cli/template_handlers.py
fastestmcp/cli/templates.py
fastestmcp/cli/test_generator.py
fastestmcp/cli/utils.py
fastestmcp/components/__init__.py
fastestmcp/components/component_loader.py
fastestmcp-1.0.3.dist-info/licenses/LICENSE
fastestmcp-1.0.3.dist-info/METADATA
fastestmcp-1.0.3.dist-info/WHEEL
fastestmcp-1.0.3.dist-info/entry_points.txt
fastestmcp-1.0.3.dist-info/top_level.txt
fastestmcp-1.0.3.dist-info/RECORD
