Metadata-Version: 2.4
Name: fastestmcp
Version: 1.0.3
Summary: Generate production-ready MCP servers and clients in seconds with the FastestMCP CLI
Home-page: https://github.com/orchestrate-solutions/fastestmcp
Author: Orchestrate LLC
Author-email: Orchestrate LLC <Joshua@orchestrate.solutions>
Requires-Python: >=3.10
License-File: LICENSE
Requires-Dist: fastmcp>=2.12.0
Requires-Dist: httpx>=0.28.0
Dynamic: author
Dynamic: home-page
Dynamic: license-file
Dynamic: requires-python
